converter/__init__.py
converter/core.py
converter/registry.py
converter/modules/__init__.py
converter/modules/audio.py
converter/modules/docx_to_pdf.py
converter/modules/image.py
converter/modules/pdf_docx_to_txt.py
converter/modules/pdf_to_docx.py
converter/modules/video.py
tests/__init__.py
convert_all-1.0.2.dist-info/LICENCE
convert_all-1.0.2.dist-info/METADATA
convert_all-1.0.2.dist-info/WHEEL
convert_all-1.0.2.dist-info/entry_points.txt
convert_all-1.0.2.dist-info/top_level.txt
convert_all-1.0.2.dist-info/RECORD
