Metadata-Version: 2.1
Name: convert-all
Version: 1.0.2
Summary: A CLI tool to convert files between formats
Home-page: https://github.com/PavlikPolivka/convert-anything
Author: Pavel Polivka
Author-email: pavel.polivka@hey.com
License: UNKNOWN
Platform: UNKNOWN
Classifier: Programming Language :: Python :: 3
Classifier: License :: OSI Approved :: MIT License
Classifier: Operating System :: OS Independent
Requires-Python: >=3.7
License-File: LICENCE
Requires-Dist: click
Requires-Dist: ffmpeg-python
Requires-Dist: Pillow
Requires-Dist: python-docx
Requires-Dist: PyMuPDF
Requires-Dist: reportlab
